[{"Class": "NMR", "ID": 1, "Method": "1H NMR"}, {"Class": "NMR", "ID": 2, "Method": "13C NMR"}, {"Class": "MS", "ID": 3, "Method": "HILIC-ESI-MS"}, {"Class": "MS", "ID": 4, "Method": "Capillary Electrophoresis with Laser-Induced Fluorescent and Mass Spectrometry Detection"}, {"Class": "MS", "ID": 5, "Method": "MALDI-ToF"}, {"Class": "MS", "ID": 6, "Method": "LC-MS"}, {"Class": null, "ID": 7, "Method": "LC-Fluorescence"}, {"Class": "NMR", "ID": 8, "Method": "1H NMR/13 NMR COSY"}, {"Class": null, "ID": 9, "Method": "HPAE-PAD"}, {"Class": "MS", "ID": 10, "Method": "UPLC-HILIC-Fluorescence-Q-ToF"}, {"Class": "MS", "ID": 11, "Method": "HILIC-HPLC-MS"}, {"Class": "MS", "ID": 12, "Method": "HPLC-Chip/TOF MS"}, {"Class": "MS", "ID": 13, "Method": "ESI-MS"}, {"Class": "MS", "ID": 14, "Method": "GLC-MS"}, {"Class": "CE", "ID": 15, "Method": "CE"}, {"Class": "MS", "ID": 16, "Method": "MALDI FT-ICR"}]
